logicmonitor/LogicMonitorClient.py
logicmonitor/__init__.py
logicmonitor-0.1.0a1.dist-info/LICENSE.txt
logicmonitor-0.1.0a1.dist-info/METADATA
logicmonitor-0.1.0a1.dist-info/RECORD
logicmonitor-0.1.0a1.dist-info/WHEEL
logicmonitor-0.1.0a1.dist-info/top_level.txt
